sqlport/__init__.py
sqlport/engine.py
sqlport/lexer.py
sqlport/logger.py
sqlport/node.py
sqlport/parser.py
sqlport/util.py
sqlport/writers/__init__.py
sqlport/writers/base.py
sqlport/writers/informix.py
sqlport/writers/postgres.py
sqlport-0.2.data/scripts/sqlport
sqlport-0.2.dist-info/DESCRIPTION.rst
sqlport-0.2.dist-info/METADATA
sqlport-0.2.dist-info/RECORD
sqlport-0.2.dist-info/WHEEL
sqlport-0.2.dist-info/metadata.json
sqlport-0.2.dist-info/top_level.txt
tests/__init__.py
tests/support.py
tests/test_parser.py
tests/test_postgres.py
