Metadata-Version: 2.0
Name: sqlport
Version: 0.2
Summary: Aspires to port Informix SQL to PostgreSQL
Home-page: https://github.com/ak-1/sqlport
Author: Andre Kuehne
Author-email: andre.kuehne.77@gmail.com
Maintainer: Andre Kuehne
Maintainer-email: andre.kuehne.77@gmail.com
License: BSD
Platform: UNKNOWN
Classifier: Programming Language :: Python :: 3
Classifier: License :: OSI Approved :: MIT License
Requires-Dist: sly
Requires-Dist: termcolor
